simplewiki/__init__.py
simplewiki/admin.py
simplewiki/admin_helper_menus.py
simplewiki/admin_helper_sections.py
simplewiki/app_settings.py
simplewiki/apps.py
simplewiki/auth_hooks.py
simplewiki/models.py
simplewiki/tasks.py
simplewiki/urls.py
simplewiki/views.py
simplewiki/views_helper.py
simplewiki/management/commands/simplewiki_migrate_v1_1.py
simplewiki/management/commands/simplewiki_migrate_v1_3.py
simplewiki/management/commands/simplewiki_migrate_v2_1.py
simplewiki/markdown/renderer.py
simplewiki/migrations/0001_initial.py
simplewiki/migrations/0002_pageitem_page_title.py
simplewiki/migrations/0003_menuitem_icon.py
simplewiki/migrations/0004_pageitem_icon_alter_menuitem_icon_and_more.py
simplewiki/migrations/0005_alter_menuitem_icon_alter_pageitem_content_and_more.py
simplewiki/migrations/0006_rename_pageitem_sectionitem.py
simplewiki/migrations/0007_rename_page_title_sectionitem_section_title.py
simplewiki/migrations/0008_alter_general_options_alter_menuitem_icon_and_more.py
simplewiki/migrations/0009_remove_menuitem_name_menuitem_path.py
simplewiki/migrations/0010_rename_path_menuitem_name.py
simplewiki/migrations/0011_rename_name_menuitem_path.py
simplewiki/migrations/0012_menuitem_group.py
simplewiki/migrations/0013_alter_menuitem_group.py
simplewiki/migrations/0014_alter_menuitem_group_alter_menuitem_icon_and_more.py
simplewiki/migrations/0015_rename_menu_name_sectionitem_menu_path_and_more.py
simplewiki/migrations/0016_rename_section_title_sectionitem_title.py
simplewiki/migrations/0017_alter_sectionitem_content_alter_sectionitem_title.py
simplewiki/migrations/0018_rename_group_menuitem_groups.py
simplewiki/migrations/0019_alter_general_options.py
simplewiki/migrations/0020_menuitem_parent.py
simplewiki/migrations/0021_alter_menuitem_index.py
simplewiki/migrations/0022_menuitem_states.py
simplewiki/migrations/0023_menu_section.py
simplewiki/migrations/0024_alter_menu_parent.py
simplewiki/migrations/0025_section_content_section_icon_section_index.py
aa_simplewiki-2.1.0.dist-info/LICENSE
aa_simplewiki-2.1.0.dist-info/METADATA
aa_simplewiki-2.1.0.dist-info/WHEEL
aa_simplewiki-2.1.0.dist-info/top_level.txt
aa_simplewiki-2.1.0.dist-info/RECORD
