Metadata-Version: 2.1
Name: aa-simplewiki
Version: 2.1.0
Summary: Alliance Auth Wiki Plugin
Home-page: https://github.com/meowosaurus/aa-simplewiki
Author: Meowosaurus
Author-email: info@bjsonnen.de
Maintainer: Meowosaurus
Maintainer-email: info@bjsonnen.de
License: GNU General Public License v3 (GPLv3)
Project-URL: Issue / Bug Reports, https://github.com/meowosaurus/aa-simplewiki/issues
Project-URL: Changelog, https://github.com/meowosaurus/aa-simplewiki/blob/master/CHANGELOG.md
Keywords: allianceauth,simplewiki
Classifier: Environment :: Web Environment
Classifier: Framework :: Django
Classifier: Intended Audience :: Developers
Classifier: License :: OSI Approved :: GNU General Public License v3 (GPLv3)
Classifier: Operating System :: OS Independent
Classifier: Programming Language :: Python :: 3.6
Classifier: Topic :: Internet :: WWW/HTTP
Classifier: Topic :: Internet :: WWW/HTTP :: Dynamic Content
Requires-Python: ~=3.8
License-File: LICENSE
Requires-Dist: mistune>=3.0.1
Requires-Dist: allianceauth>=4.0.0
Requires-Dist: allianceauth-app-utils
